{"team": {"id": "4235", "nameShow": "Granada", "basealias": "granada", "CountryCode": "ES", "location": null, "geoId": "2517117", "geonameid": "2517117", "basename": "Granada C.F.", "stadium": "Nuevo Los C\u00e1rmenes", "mainId": "4235", "mainId_type": "1", "short_name": "GRA", "managerNow": "Paco L\u00f3pez", "seats": "19336", "website": "http://www.granadacf.es", "yearFoundation": "1931", "city": "Granada", "address": "Calle Pintor Manuel Maldonado, s/n, 18007, Granada", "phone": "958 253 300", "fax": "958 253 304", "chairman": "Sophia Yang", "fullName": "Granada Club de F\u00fatbol SAD", "yearlyBudget": null, "info": null, "fans": "13800", "typefield": "Natural", "ctype": "1", "yearBuilt": "1995", "size": "105 x 69 metros", "historical": "Campe\u00f3n absoluto de Segunda Divisi\u00f3n B en la temporada 2009/2010. Subcampe\u00f3n de la Copa del Rey en la temporada 1958/1959. Tres veces semifinalista en la Copa del Rey. Doce veces en los cuartos de la Copa del Rey  ", "comments": "0", "color1": "a61b2b", "color2": "#FFFFFF", "kit_home": "", "kit_away": "", "kit_third": "", "twitter": "@GranadaCF", "twitter_coach": null, "twitter_president": null, "twitter_b": null, "qod": "75", "pod": "1040", "last_change": "2023-10-12 09:30:56", "relations": "198", "relatedImg": null, "basealias_old": null, "nameAux": null, "patrocinador": null, "patrocinador_b": null, "team_b": "Granada B", "proveedor": "Adidas", "lugar_entrenamiento": "Ciudad Deportiva del Granada CF", "repeat_year": "2011", "no_year": "1994,1995,1996,1997,1998,1999,2000,2001,2002,2003,2004,2005,2006,2007,2008,2009", "error_date": "2013-07-29 12:47:16", "fifaId": "241", "main_image": "1", "image_mdate": "2017-06-29 12:43:06", "type_team": "0", "active_relations": "2", "match_played": "437", "match_to_play": "438", "localidad": null, "hid": "0000000059", "hid_B": "0", "translate": "0", "email": "secretaria@granadacf.es", "elo": "1535", "int": "0", "int_sub": "0", "admin_workers": null, "sports_workers": null, "social_mass": null, "squadyearlybudget": null, "debt": "12.24", "social_followers": "751.67", "extinct_year": null, "nameExtTv": "Granada CF", "gender": 1, "Name": "Espa\u00f1a", "Continent": "Europa", "Region": "Europa del Sur", "latitude": "37.1881700", "longitude": "-3.6066700", "geo_location": "Granada", "presidentNow": "Sophia Yang", "shield": "https://t.resfu.com/img_data/escudos/medium/4235.jpg?size=120x&lossy=1&v=36", "img_stadium": "https://cdn.resfu.com/img_data/estadios/original_new/27.jpg?size=640x460&lossy=1&v=36", "team_flag": "https://t.resfu.com/media/img/flags/st3/large/es.png?size=100x65c&lossy=1&v=36", "category": {"troncal": "1", "conference": "0", "category_id": "1", "team_id": "6583641", "league_id": "72116", "cat_name": "Primera Divisi\u00f3n", "cat_name_en": "LaLiga", "year": "2024", "tables": "1", "current_round": "12", "group_code": "1", "total_group": "1", "active_year": "2024", "alias": "primera", "table_suffix": null, "league_logo": "https://t.resfu.com/media/img/league_logos/primera-division-ea.png?size=60x&lossy=1&v=36", "completeName": "Primera Divisi\u00f3n", "completeNameEn": "LaLiga", "completeAlias": "primera"}, "competitions": [{"id": "1", "team_id": "6583641", "coef": "82.500", "name": "Primera Divisi\u00f3n", "alias": "primera", "year": "2024", "continent": "eu", "flag": "https://t.resfu.com/media/img/flags/st3/large/es.png?size=100x65c&lossy=1&v=36", "logo": "https://t.resfu.com/media/img/league_logos/primera-division-ea.png?size=120x&lossy=1&v=36", "phases": [{"id": "1", "league_id": "72116", "group": "1", "type": "group", "current_round": "12", "total_rounds": "38", "total_teams": "20", "team_group": true, "is_current": true}]}, {"id": "129", "team_id": "6577282", "coef": "64.600", "name": "Copa del Rey", "alias": "copa_del_rey", "year": "2024", "continent": "eu", "flag": "https://t.resfu.com/media/img/flags/st3/large/es.png?size=100x65c&lossy=1&v=36", "logo": "https://t.resfu.com/media/img/league_logos/copa-del-rey.png?size=120x&lossy=1&v=36", "phases": [{"id": "129", "league_id": "71759", "group": "playoff", "type": "playoffs", "current_round": "2", "total_rounds": "8", "total_teams": "125", "team_group": true}]}], "position": 19, "tables": [{"nameShow": "Girona", "diff": "114", "points": "31", "gf": "29", "ga": "15", "win_h": "5", "draw_h": "0", "lose_h": "1", "win_a": "5", "draw_a": "1", "lose_a": "0", "team": "6583640", "league_id": "72116", "round": "12", "team_name": "Girona", "form": "dwwwwwwlwwww", "form_res": "|1-1-0463856-8463856|0-3-9363856-0463856|2-1-0463856-9463856|0-1-2463856-0463856|4-2-0463856-1463856|3-5-3463856-0463856|2-1-0463856-1563856|3-0-7463856-0463856|1-0-0463856-3363856|2-5-5363856-0463856|0-1-8363856-0463856|4-2-0463856-4463856", "priority": "0", "position": 1, "teamId": "1236"}, {"nameShow": "Real Madrid", "diff": "115", "points": "29", "gf": "23", "ga": "8", "win_h": "4", "draw_h": "1", "lose_h": "0", "win_a": "5", "draw_a": "1", "lose_a": "1", "team": "6583647", "league_id": "72116", "round": "12", "team_name": "Real Madrid", "form": "wwwwwlwwwdwd", "form_res": "|2-0-7463856-6363856|3-1-7463856-5363856|1-0-7463856-8363856|1-2-9363856-7463856|1-2-8463856-7463856|1-3-7463856-7363856|0-2-2463856-7463856|3-0-7463856-0463856|0-4-4463856-7463856|1-1-7463856-9463856|2-1-7463856-4363856|0-0-5463856-7463856", "priority": "0", "position": 2, "teamId": "2107"}, {"nameShow": "Barcelona", "diff": "112", "points": "27", "gf": "24", "ga": "12", "win_h": "5", "draw_h": "0", "lose_h": "1", "win_a": "3", "draw_a": "3", "lose_a": "0", "team": "6583634", "league_id": "72116", "round": "12", "team_name": "Barcelona", "form": "dwwwwwdwdwlw", "form_res": "|0-0-4363856-9363856|0-2-3363856-4363856|4-3-4363856-1563856|2-1-4363856-4463856|0-5-6463856-4363856|2-3-8363856-4363856|2-2-4363856-3463856|0-1-9463856-4363856|2-2-4363856-1463856|0-1-6363856-4363856|2-1-7463856-4363856|1-0-4363856-8463856", "priority": "0", "position": 3, "teamId": "429"}, {"nameShow": "Atl\u00e9tico", "diff": "115", "points": "25", "gf": "26", "ga": "11", "win_h": "5", "draw_h": "0", "lose_h": "0", "win_a": "3", "draw_a": "1", "lose_a": "2", "team": "6583637", "league_id": "72116", "round": "12", "team_name": "Atl\u00e9tico", "form": "wdwlwwwwwwl", "form_res": "|1-3-1463856-7363856|0-0-7363856-6463856|7-0-7363856-5463856|0-3-7363856-0563856|1-3-7463856-7363856|2-0-7363856-4463856|2-3-3363856-7363856|1-2-8463856-7363856|3-0-7363856-8363856|1-2-6614856-7363856|1-2-7363856-2463856", "priority": "0", "position": 4, "teamId": "369"}, {"nameShow": "Athletic", "diff": "107", "points": "21", "gf": "21", "ga": "14", "win_h": "3", "draw_h": "2", "lose_h": "1", "win_a": "3", "draw_a": "1", "lose_a": "2", "team": "6583636", "league_id": "72116", "round": "12", "team_name": "Athletic", "form": "lwwdwwdlwldw", "form_res": "|2-0-7463856-6363856|2-0-6363856-4463856|2-4-6463856-6363856|0-0-6363856-3463856|0-3-3363856-6363856|2-0-6363856-6614856|2-2-9363856-6363856|0-3-6363856-8463856|0-3-5363856-6363856|0-1-6363856-4363856|2-2-0563856-6363856|3-2-6363856-1563856", "priority": "0", "position": 5, "teamId": "347"}, {"nameShow": "Real Betis", "diff": "101", "points": "20", "gf": "16", "ga": "15", "win_h": "4", "draw_h": "2", "lose_h": "0", "win_a": "1", "draw_a": "3", "lose_a": "2", "team": "6583646", "league_id": "72116", "round": "12", "team_name": "Real Betis", "form": "wdlwlddwddww", "form_res": "|2-1-6463856-1563856|0-0-7363856-6463856|2-4-6463856-6363856|0-1-5463856-6463856|0-5-6463856-4363856|1-1-3363856-6463856|1-1-6463856-1463856|0-3-0563856-6463856|1-1-6463856-6614856|1-1-6463856-9363856|1-2-4463856-6463856|0-2-3463856-6463856", "priority": "0", "position": 6, "teamId": "486"}, {"nameShow": "Real Sociedad", "diff": "105", "points": "19", "gf": "20", "ga": "15", "win_h": "4", "draw_h": "2", "lose_h": "1", "win_a": "1", "draw_a": "2", "lose_a": "2", "team": "6583648", "league_id": "72116", "round": "12", "team_name": "Real Sociedad", "form": "dddwlwwwlwdl", "form_res": "|1-1-0463856-8463856|1-1-8363856-8463856|0-0-8463856-2463856|3-5-1463856-8463856|1-2-8463856-7463856|3-4-9363856-8463856|1-0-8463856-0563856|0-3-6363856-8463856|1-2-8463856-7363856|0-1-3463856-8463856|2-2-8463856-5463856|1-0-4363856-8463856", "priority": "0", "position": 7, "teamId": "2120"}, {"nameShow": "Valencia", "diff": "102", "points": "18", "gf": "15", "ga": "13", "win_h": "4", "draw_h": "0", "lose_h": "2", "win_a": "1", "draw_a": "3", "lose_a": "2", "team": "6583650", "league_id": "72116", "round": "12", "team_name": "Valencia", "form": "wwllwdlldwdw", "form_res": "|2-1-0563856-9463856|0-1-2463856-0563856|2-1-4463856-0563856|0-1-0563856-6614856|0-3-7363856-0563856|2-2-0563856-5363856|1-0-8463856-0563856|0-3-0563856-6463856|1-1-0563856-3463856|0-2-3363856-0563856|2-2-0563856-6363856|0-1-1463856-0563856", "priority": "0", "position": 8, "teamId": "2647"}, {"nameShow": "Rayo Vallecano", "diff": "99", "points": "18", "gf": "14", "ga": "15", "win_h": "1", "draw_h": "3", "lose_h": "1", "win_a": "3", "draw_a": "3", "lose_a": "1", "team": "6583645", "league_id": "72116", "round": "12", "team_name": "Rayo Vallecano", "form": "wwllwddddwdd", "form_res": "|2-0-5463856-5363856|2-0-5463856-1463856|7-0-7363856-5463856|0-1-5463856-6463856|0-2-6614856-5463856|1-1-1563856-5463856|0-0-5463856-3363856|2-2-3463856-5463856|2-2-5463856-9463856|1-0-5463856-2463856|2-2-8463856-5463856|0-0-5463856-7463856", "priority": "0", "position": 9, "teamId": "2080"}, {"nameShow": "Las Palmas", "diff": "99", "points": "17", "gf": "10", "ga": "11", "win_h": "3", "draw_h": "2", "lose_h": "1", "win_a": "2", "draw_a": "0", "lose_a": "4", "team": "6583642", "league_id": "72116", "round": "12", "team_name": "Las Palmas", "form": "dldllwlwwlww", "form_res": "|1-1-3463856-2463856|0-1-2463856-0563856|0-0-8463856-2463856|0-1-2463856-0463856|0-1-2463856-9463856|0-1-1463856-2463856|0-2-2463856-7463856|1-2-8363856-2463856|2-1-2463856-1563856|1-0-5463856-2463856|2-1-2463856-5363856|1-2-7363856-2463856", "priority": "0", "position": 10, "teamId": "2563"}, {"nameShow": "Getafe", "diff": "98", "points": "15", "gf": "14", "ga": "16", "win_h": "3", "draw_h": "3", "lose_h": "0", "win_a": "0", "draw_a": "3", "lose_a": "3", "team": "6583639", "league_id": "72116", "round": "12", "team_name": "Getafe", "form": "dlwlwldddddw", "form_res": "|0-0-4363856-9363856|0-3-9363856-0463856|0-1-6614856-9363856|1-2-9363856-7463856|2-3-4463856-9363856|3-4-9363856-8463856|2-2-9363856-6363856|0-0-1563856-9363856|2-2-9363856-8363856|1-1-6463856-9363856|0-0-9363856-3463856|0-1-3363856-9363856", "priority": "0", "position": 11, "teamId": "1217"}, {"nameShow": "Osasuna", "diff": "94", "points": "13", "gf": "14", "ga": "20", "win_h": "1", "draw_h": "1", "lose_h": "4", "win_a": "3", "draw_a": "0", "lose_a": "3", "team": "6583644", "league_id": "72116", "round": "12", "team_name": "Osasuna", "form": "wlwlldlwlwll", "form_res": "|2-0-4463856-8363856|2-0-6363856-4463856|2-1-4463856-0563856|2-1-4363856-4463856|2-3-4463856-9363856|0-0-9463856-4463856|2-0-7363856-4463856|2-0-4463856-6614856|0-4-4463856-7463856|0-2-1463856-4463856|1-2-4463856-6463856|4-2-0463856-4463856", "priority": "0", "position": 12, "teamId": "1887"}, {"nameShow": "Villarreal", "diff": "96", "points": "12", "gf": "17", "ga": "21", "win_h": "1", "draw_h": "1", "lose_h": "5", "win_a": "2", "draw_a": "2", "lose_a": "1", "team": "6583651", "league_id": "72116", "round": "12", "team_name": "Villarreal", "form": "lwllwdldldwl", "form_res": "|2-1-6463856-1563856|1-0-1563856-3463856|4-3-4363856-1563856|1-3-1563856-3363856|1-2-5363856-1563856|1-1-1563856-5463856|2-1-0463856-1563856|0-0-1563856-9363856|2-1-2463856-1563856|1-1-6614856-1563856|3-2-1563856-1463856|3-2-6363856-1563856", "priority": "0", "position": 13, "teamId": "2716"}, {"nameShow": "Deportivo Alav\u00e9s", "diff": "94", "points": "12", "gf": "10", "ga": "16", "win_h": "3", "draw_h": "1", "lose_h": "2", "win_a": "0", "draw_a": "2", "lose_a": "4", "team": "6584166", "league_id": "72116", "round": "12", "team_name": "Deportivo Alav\u00e9s", "form": "lwlwlldlddlw", "form_res": "|0-1-6614856-3363856|3-4-9463856-6614856|0-1-6614856-9363856|0-1-0563856-6614856|0-2-6614856-5463856|2-0-6363856-6614856|1-1-6614856-8363856|2-0-4463856-6614856|1-1-6463856-6614856|1-1-6614856-1563856|1-2-6614856-7363856|0-1-5363856-6614856", "priority": "0", "position": 14, "teamId": "137"}, {"nameShow": "Sevilla", "diff": "101", "points": "11", "gf": "17", "ga": "16", "win_h": "2", "draw_h": "2", "lose_h": "2", "win_a": "0", "draw_a": "3", "lose_a": "2", "team": "6583649", "league_id": "72116", "round": "12", "team_name": "Sevilla", "form": "lllwdwldddd", "form_res": "|2-1-0563856-9463856|3-4-9463856-6614856|2-1-0463856-9463856|0-1-2463856-9463856|0-0-9463856-4463856|1-5-5363856-9463856|0-1-9463856-4363856|2-2-5463856-9463856|1-1-7463856-9463856|2-2-9463856-3363856|1-1-9463856-8363856", "priority": "0", "position": 15, "teamId": "1102"}, {"nameShow": "C\u00e1diz", "diff": "93", "points": "10", "gf": "10", "ga": "17", "win_h": "2", "draw_h": "3", "lose_h": "1", "win_a": "0", "draw_a": "1", "lose_a": "5", "team": "6583633", "league_id": "72116", "round": "12", "team_name": "C\u00e1diz", "form": "wldwlddllldl", "form_res": "|0-1-6614856-3363856|0-2-3363856-4363856|1-1-5363856-3363856|1-3-1563856-3363856|0-3-3363856-6363856|1-1-3363856-6463856|0-0-5463856-3363856|2-3-3363856-7363856|1-0-0463856-3363856|0-2-3363856-0563856|2-2-9463856-3363856|0-1-3363856-9363856", "priority": "0", "position": 16, "teamId": "603"}, {"nameShow": "Mallorca", "diff": "94", "points": "9", "gf": "12", "ga": "18", "win_h": "0", "draw_h": "4", "lose_h": "1", "win_a": "1", "draw_a": "2", "lose_a": "4", "team": "6583643", "league_id": "72116", "round": "12", "team_name": "Mallorca", "form": "dlldwldddldl", "form_res": "|1-1-3463856-2463856|1-0-1563856-3463856|2-3-3463856-1463856|0-0-6363856-3463856|1-0-3463856-8363856|3-5-3463856-0463856|2-2-4363856-3463856|2-2-3463856-5463856|1-1-0563856-3463856|0-1-3463856-8463856|0-0-9363856-3463856|0-2-3463856-6463856", "priority": "0", "position": 17, "teamId": "1623"}, {"nameShow": "Celta", "diff": "91", "points": "7", "gf": "11", "ga": "20", "win_h": "0", "draw_h": "3", "lose_h": "4", "win_a": "1", "draw_a": "1", "lose_a": "3", "team": "6583638", "league_id": "72116", "round": "12", "team_name": "Celta", "form": "ldlwlldldlld", "form_res": "|2-0-4463856-8363856|1-1-8363856-8463856|1-0-7463856-8363856|3-2-8363856-5363856|1-0-3463856-8363856|2-3-8363856-4363856|1-1-6614856-8363856|1-2-8363856-2463856|2-2-9363856-8363856|3-0-7363856-8363856|0-1-8363856-0463856|1-1-9463856-8363856", "priority": "0", "position": 18, "teamId": "712"}, {"nameShow": "Granada", "diff": "88", "points": "6", "gf": "17", "ga": "29", "win_h": "1", "draw_h": "2", "lose_h": "3", "win_a": "0", "draw_a": "1", "lose_a": "5", "team": "6583641", "league_id": "72116", "round": "12", "team_name": "Granada", "form": "llwllldddlll", "form_res": "|1-3-1463856-7363856|2-0-5463856-1463856|2-3-3463856-1463856|3-5-1463856-8463856|4-2-0463856-1463856|0-1-1463856-2463856|1-1-6463856-1463856|3-3-1463856-5363856|2-2-4363856-1463856|0-2-1463856-4463856|3-2-1563856-1463856|0-1-1463856-0563856", "priority": "0", "position": 19, "teamId": "4235"}, {"nameShow": "Almer\u00eda", "diff": "82", "points": "3", "gf": "14", "ga": "32", "win_h": "0", "draw_h": "2", "lose_h": "4", "win_a": "0", "draw_a": "1", "lose_a": "5", "team": "6583635", "league_id": "72116", "round": "12", "team_name": "Almer\u00eda", "form": "lldlldldllll", "form_res": "|2-0-5463856-5363856|3-1-7463856-5363856|1-1-5363856-3363856|3-2-8363856-5363856|1-2-5363856-1563856|2-2-0563856-5363856|1-5-5363856-9463856|3-3-1463856-5363856|0-3-5363856-6363856|2-5-5363856-0463856|2-1-2463856-5363856|0-1-5363856-6614856", "priority": "0", "position": 20, "teamId": "183"}], "squad": [{"id": "319035", "nick": "Adri L\u00f3pez", "name": "Adri\u00e1n", "last_name": "L\u00f3pez Garrote", "alias": "a-lopez-319035", "birthdate": "1999-01-09", "height": "188", "weight": "73", "foot": "1", "side": "0", "role": "1", "year": "2024", "squadNumber": "31", "num": "", "pos": "", "idplayer": "", "goals": "", "reds": "", "yellows": "", "CountryCode": "ES", "gender": null, "image": "https://t.resfu.com/img_data/players/medium/319035.jpg?size=60x&lossy=1&v=36"}, {"id": "207066", "nick": "Andr\u00e9 Ferreira", "name": "Andr\u00e9 Filipe", "last_name": "Magalh\u00e3es Ribeiro Ferreira", "alias": "a-ferreira-207066", "birthdate": "1996-05-29", "height": "193", "weight": "79", "foot": "1", "side": "0", "role": "1", "year": "2024", "squadNumber": "13", "num": "", "pos": "", "idplayer": "", "goals": "", "reds": "", "yellows": "", "CountryCode": "PT", "gender": null, "image": "https://t.resfu.com/img_data/players/medium/207066.jpg?size=60x&lossy=1&v=36"}, {"id": "34268", "nick": "Ra\u00fal Fern\u00e1ndez", "name": "Ra\u00fal", "last_name": "Fern\u00e1ndez-Cavada Mateos", "alias": "raul-fernandez-34268", "birthdate": "1988-03-13", "height": "195", "weight": "92", "foot": "1", "side": "1", "role": "1", "year": "2024", "squadNumber": "1", "num": "", "pos": "", "idplayer": "", "goals": "", "reds": "", "yellows": "", "CountryCode": "ES", "gender": null, "image": "https://t.resfu.com/img_data/players/medium/34268.jpg?size=60x&lossy=1&v=36"}, {"id": "975472", "nick": "\u00c1. Carreras", "name": "\u00c1lvaro", "last_name": "Fern\u00e1ndez Carreras", "alias": "a-fernandez-975472", "birthdate": "2003-03-23", "height": "186", "weight": "70", "foot": "2", "side": "0", "role": "2", "year": "2024", "squadNumber": "33", "num": "", "pos": "", "idplayer": "", "goals": "", "reds": "", "yellows": "", "CountryCode": "ES", "gender": "1", "image": "https://t.resfu.com/img_data/players/medium/975472.jpg?size=60x&lossy=1&v=36"}, {"id": "222400", "nick": "Carlos Neva", "name": "Carlos", "last_name": "Neva Tey", "alias": "neva-222400", "birthdate": "1996-06-12", "height": "174", "weight": "64", "foot": "2", "side": "3", "role": "2", "year": "2024", "squadNumber": "15", "num": "", "pos": "", "idplayer": "", "goals": "", "reds": "", "yellows": "", "CountryCode": "ES", "gender": null, "image": "https://t.resfu.com/img_data/players/medium/222400.jpg?size=60x&lossy=1&v=36"}, {"id": "94400", "nick": "Ignasi Miquel", "name": "Ignasi", "last_name": "Miquel Pons", "alias": "i-miquel-94400", "birthdate": "1992-09-28", "height": "189", "weight": "82", "foot": "2", "side": "1", "role": "2", "year": "2024", "squadNumber": "14", "num": "", "pos": "", "idplayer": "", "goals": "", "reds": "", "yellows": "", "CountryCode": "ES", "gender": null, "image": "https://t.resfu.com/img_data/players/medium/94400.jpg?size=60x&lossy=1&v=36"}, {"id": "171872", "nick": "Jes\u00fas Vallejo", "name": "Jes\u00fas", "last_name": "Vallejo L\u00e1zaro", "alias": "vallejo-lazaro-jesus-171872", "birthdate": "1997-01-05", "height": "184", "weight": "79", "foot": "1", "side": "1", "role": "2", "year": "2024", "squadNumber": "5", "num": "", "pos": "", "idplayer": "", "goals": "", "reds": "", "yellows": "", "CountryCode": "ES", "gender": null, "image": "https://t.resfu.com/img_data/players/medium/171872.jpg?size=60x&lossy=1&v=36"}, {"id": "423294", "nick": "Miguel Rubio", "name": "Miguel \u00c1ngel", "last_name": "Rubio Lestan", "alias": "miguel-423294", "birthdate": "1998-03-11", "height": "191", "weight": "80", "foot": "1", "side": "1", "role": "2", "year": "2024", "squadNumber": "4", "num": "", "pos": "", "idplayer": "", "goals": "", "reds": "", "yellows": "", "CountryCode": "ES", "gender": null, "image": "https://t.resfu.com/img_data/players/medium/423294.jpg?size=60x&lossy=1&v=36"}, {"id": "760055", "nick": "Miki Bosch", "name": "Adri\u00e1 Miquel", "last_name": "Bosch Sanch\u00eds", "alias": "a-bosch-760055", "birthdate": "2001-06-09", "height": "190", "weight": "78", "foot": "1", "side": "0", "role": "2", "year": "2024", "squadNumber": "32", "num": "", "pos": "", "idplayer": "", "goals": "", "reds": "", "yellows": "", "CountryCode": "ES", "gender": null, "image": "https://t.resfu.com/img_data/players/medium/760055.jpg?size=60x&lossy=1&v=36"}, {"id": "665858", "nick": "Ra\u00fal Torrente", "name": "Ra\u00fal", "last_name": "Torrente Navarro", "alias": "r-torrente-665858", "birthdate": "2001-09-11", "height": "193", "weight": "79", "foot": "2", "side": "0", "role": "2", "year": "2024", "squadNumber": "28", "num": "", "pos": "", "idplayer": "", "goals": "", "reds": "", "yellows": "", "CountryCode": "ES", "gender": null, "image": "https://t.resfu.com/img_data/players/medium/665858.jpg?size=60x&lossy=1&v=36"}, {"id": "752814", "nick": "Ricard S\u00e1nchez", "name": "Ricard", "last_name": "S\u00e1nchez Sendra", "alias": "r-sanchez-752814", "birthdate": "2000-02-22", "height": "175", "weight": "67", "foot": "1", "side": "0", "role": "2", "year": "2024", "squadNumber": "12", "num": "", "pos": "", "idplayer": "", "goals": "", "reds": "", "yellows": "", "CountryCode": "ES", "gender": null, "image": "https://t.resfu.com/img_data/players/medium/752814.jpg?size=60x&lossy=1&v=36"}, {"id": "40792", "nick": "V\u00edctor D\u00edaz", "name": "V\u00edctor David", "last_name": "D\u00edaz Miguel", "alias": "victor-diaz-40792", "birthdate": "1988-06-12", "height": "183", "weight": "71", "foot": "1", "side": "2", "role": "2", "year": "2024", "squadNumber": "16", "num": "", "pos": "", "idplayer": "", "goals": "", "reds": "", "yellows": "", "CountryCode": "ES", "gender": null, "image": "https://t.resfu.com/img_data/players/medium/40792.jpg?size=60x&lossy=1&v=36"}, {"id": "199088", "nick": "Wilson Manaf\u00e1", "name": "Wilson Migueis", "last_name": "Manaf\u00e1 Janc\u00f3", "alias": "wilson-manafa-199088", "birthdate": "1994-07-23", "height": "177", "weight": "72", "foot": "1", "side": "3", "role": "2", "year": "2024", "squadNumber": "3", "num": "", "pos": "", "idplayer": "", "goals": "", "reds": "", "yellows": "", "CountryCode": "PT", "gender": null, "image": "https://t.resfu.com/img_data/players/medium/199088.jpg?size=60x&lossy=1&v=36"}, {"id": "192553", "nick": "G. Gumbau", "name": "Gerard", "last_name": "Gumbau Garriga", "alias": "gerard-gumbau-192553", "birthdate": "1994-12-18", "height": "188", "weight": "77", "foot": "2", "side": "0", "role": "3", "year": "2024", "squadNumber": "23", "num": "", "pos": "", "idplayer": "", "goals": "", "reds": "", "yellows": "", "CountryCode": "ES", "gender": null, "image": "https://t.resfu.com/img_data/players/medium/192553.jpg?size=60x&lossy=1&v=36"}, {"id": "290051", "nick": "Gonzalo Villar", "name": "Gonzalo", "last_name": "Villar Del Fraile", "alias": "g-villar-290051", "birthdate": "1998-03-23", "height": "181", "weight": "74", "foot": "1", "side": "0", "role": "3", "year": "2024", "squadNumber": "24", "num": "", "pos": "", "idplayer": "", "goals": "", "reds": "", "yellows": "", "CountryCode": "ES", "gender": null, "image": "https://t.resfu.com/img_data/players/medium/290051.jpg?size=60x&lossy=1&v=36"}, {"id": "992936", "nick": "Mario Gonz\u00e1lez", "name": "Mario", "last_name": "Gonz\u00e1lez Bravo", "alias": "mario-992936", "birthdate": "2004-02-05", "height": "174", "weight": "61", "foot": "1", "side": "0", "role": "3", "year": "2024", "squadNumber": "27", "num": "", "pos": "", "idplayer": "", "goals": "", "reds": "", "yellows": "", "CountryCode": "ES", "gender": "1", "image": "https://t.resfu.com/img_data/players/medium/992936.jpg?size=60x&lossy=1&v=36"}, {"id": "320807", "nick": "N. Petrovi\u0107", "name": "Njego\u0161", "last_name": "Petrovi\u0107", "alias": "n-petrovic-320807", "birthdate": "1999-07-18", "height": "185", "weight": "72", "foot": "1", "side": "0", "role": "3", "year": "2024", "squadNumber": "18", "num": "", "pos": "", "idplayer": "", "goals": "", "reds": "", "yellows": "", "CountryCode": "RS", "gender": null, "image": "https://t.resfu.com/img_data/players/medium/320807.jpg?size=60x&lossy=1&v=36"}, {"id": "333261", "nick": "\u00d3scar Melendo", "name": "\u00d3scar", "last_name": "Melendo Jim\u00e9nez", "alias": "o-melendo-333261", "birthdate": "1997-08-23", "height": "167", "weight": "63", "foot": "2", "side": "0", "role": "3", "year": "2024", "squadNumber": "21", "num": "", "pos": "", "idplayer": "", "goals": "", "reds": "", "yellows": "", "CountryCode": "ES", "gender": null, "image": "https://t.resfu.com/img_data/players/medium/333261.jpg?size=60x&lossy=1&v=36"}, {"id": "283970", "nick": "Sergio Ruiz", "name": "Sergio", "last_name": "Ruiz Alonso", "alias": "s-ruiz-283970", "birthdate": "1994-12-16", "height": "176", "weight": "70", "foot": "1", "side": "0", "role": "3", "year": "2024", "squadNumber": "20", "num": "", "pos": "", "idplayer": "", "goals": "", "reds": "", "yellows": "", "CountryCode": "ES", "gender": null, "image": "https://t.resfu.com/img_data/players/medium/283970.jpg?size=60x&lossy=1&v=36"}, {"id": "68846", "nick": "Alberto Perea", "name": "Alberto", "last_name": "Perea Correoso", "alias": "a-perea-68846", "birthdate": "1990-12-19", "height": "175", "weight": "68", "foot": "1", "side": "2", "role": "4", "year": "2024", "squadNumber": "22", "num": "", "pos": "", "idplayer": "", "goals": "", "reds": "", "yellows": "", "CountryCode": "ES", "gender": null, "image": "https://t.resfu.com/img_data/players/medium/68846.jpg?size=60x&lossy=1&v=36"}, {"id": "134656", "nick": "Antonio Puertas", "name": "Antonio Jos\u00e9", "last_name": "Rodr\u00edguez D\u00edaz", "alias": "antonio-puertas-134656", "birthdate": "1992-02-21", "height": "183", "weight": "77", "foot": "1", "side": "1", "role": "4", "year": "2024", "squadNumber": "10", "num": "", "pos": "", "idplayer": "", "goals": "", "reds": "", "yellows": "", "CountryCode": "ES", "gender": null, "image": "https://t.resfu.com/img_data/players/medium/134656.jpg?size=60x&lossy=1&v=36"}, {"id": "950490", "nick": "Bryan Zaragoza", "name": "Bryan", "last_name": "Zaragoza Mart\u00ednez", "alias": "bryan-950490", "birthdate": "2001-09-09", "height": "164", "weight": "61", "foot": "1", "side": "3", "role": "4", "year": "2024", "squadNumber": "26", "num": "", "pos": "", "idplayer": "", "goals": "", "reds": "", "yellows": "", "CountryCode": "ES", "gender": "1", "image": "https://t.resfu.com/img_data/players/medium/950490.jpg?size=60x&lossy=1&v=36"}, {"id": "212542", "nick": "F. Di\u00e9dhiou", "name": "Famara", "last_name": "Di\u00e9dhiou", "alias": "f-diedhiou-212542", "birthdate": "1992-12-15", "height": "189", "weight": "80", "foot": "1", "side": "0", "role": "4", "year": "2024", "squadNumber": "19", "num": "", "pos": "", "idplayer": "", "goals": "", "reds": "", "yellows": "", "CountryCode": "SN", "gender": null, "image": "https://t.resfu.com/img_data/players/medium/212542.jpg?size=60x&lossy=1&v=36"}, {"id": "23361", "nick": "Jos\u00e9 Callej\u00f3n", "name": "Jos\u00e9 Mar\u00eda", "last_name": "Callej\u00f3n Bueno", "alias": "j-callejon-23361", "birthdate": "1987-02-11", "height": "178", "weight": "73", "foot": "1", "side": "2", "role": "4", "year": "2024", "squadNumber": "9", "num": "", "pos": "", "idplayer": "", "goals": "", "reds": "", "yellows": "", "CountryCode": "ES", "gender": null, "image": "https://t.resfu.com/img_data/players/medium/23361.jpg?size=60x&lossy=1&v=36"}, {"id": "230939", "nick": "Lucas Boy\u00e9", "name": "Lucas", "last_name": "Boy\u00e9", "alias": "l-boye-230939", "birthdate": "1996-02-28", "height": "183", "weight": "83", "foot": "1", "side": "0", "role": "4", "year": "2024", "squadNumber": "7", "num": "", "pos": "", "idplayer": "", "goals": "", "reds": "", "yellows": "", "CountryCode": "AR", "gender": null, "image": "https://t.resfu.com/img_data/players/medium/230939.jpg?size=60x&lossy=1&v=36"}, {"id": "283717", "nick": "Myrto Uzuni", "name": "Myrto", "last_name": "Uzuni", "alias": "m-uzuni-283717", "birthdate": "1995-05-31", "height": "178", "weight": "70", "foot": "1", "side": "0", "role": "4", "year": "2024", "squadNumber": "11", "num": "", "pos": "", "idplayer": "", "goals": "", "reds": "", "yellows": "", "CountryCode": "AL", "gender": null, "image": "https://t.resfu.com/img_data/players/medium/283717.jpg?size=60x&lossy=1&v=36"}, {"id": "229477", "nick": "S. Weissman", "name": "Shon Zalman", "last_name": "Weissman", "alias": "s-weissman-229477", "birthdate": "1996-02-14", "height": "174", "weight": "69", "foot": "1", "side": "0", "role": "4", "year": "2024", "squadNumber": "17", "num": "", "pos": "", "idplayer": "", "goals": "", "reds": "", "yellows": "", "CountryCode": "IL", "gender": null, "image": "https://t.resfu.com/img_data/players/medium/229477.jpg?size=60x&lossy=1&v=36"}], "t_squad": 27, "hasNews": true, "hasTransfers": true}}